secscanner2junit/__init__.py
secscanner2junit/config.py
secscanner2junit/container_scanning.py
secscanner2junit/logger.py
secscanner2junit/parser.py
secscanner2junit/sast.py
secscanner2junit/secrets.py
secscanner2junit/vulnerability.py
secscanner2junit-0.1.18.dist-info/LICENSE
secscanner2junit-0.1.18.dist-info/METADATA
secscanner2junit-0.1.18.dist-info/WHEEL
secscanner2junit-0.1.18.dist-info/entry_points.txt
secscanner2junit-0.1.18.dist-info/RECORD
