Metadata-Version: 2.3
Name: secscanner2junit
Version: 0.1.18
Summary: Convert Security Scanner Output to JUnit Format
License: GPL-3.0-only
Author: Florian Angermeir
Author-email: florian.angermeir@tum.de
Requires-Python: >=3.10,<4.0
Classifier: License :: OSI Approved :: GNU General Public License v3 (GPLv3)
Classifier: Programming Language :: Python :: 3
Classifier: Programming Language :: Python :: 3.10
Classifier: Programming Language :: Python :: 3.11
Classifier: Programming Language :: Python :: 3.12
Classifier: Programming Language :: Python :: 3.13
Requires-Dist: PyYAML (>=6.0,<7.0)
Requires-Dist: junit-xml (>=1.9,<2.0)
Requires-Dist: pytest (>=7.2.0,<8.0.0)
Requires-Dist: setuptools (>=75.5.0,<76.0.0)
Project-URL: Homepage, https://github.com/angrymeir/SecScanner2JUnit
Project-URL: Repository, https://github.com/angrymeir/SecScanner2JUnit
